wiener_netze_smart_meter_api/__about__.py
wiener_netze_smart_meter_api/__init__.py
wiener_netze_smart_meter_api/client.py
wiener_netze_smart_meter_api/example.py
wiener_netze_smart_meter_api/exceptions.py
wiener_netze_smart_meter_api-0.1.4.dist-info/METADATA
wiener_netze_smart_meter_api-0.1.4.dist-info/WHEEL
wiener_netze_smart_meter_api-0.1.4.dist-info/licenses/LICENSE.txt
wiener_netze_smart_meter_api-0.1.4.dist-info/RECORD
