Metadata-Version: 2.4
Name: wiener-netze-smart-meter-api
Version: 0.1.4
Summary: A Python wrapper for the official Wiener Netze Smart Meter API (WN_SMART_METER_API)
Project-URL: Documentation, https://github.com/tschoerk/Wiener-Netze-Smart-Meter-API#readme
Project-URL: Issues, https://github.com/tschoerk/Wiener-Netze-Smart-Meter-API/issues
Project-URL: Source, https://github.com/tschoerk/Wiener-Netze-Smart-Meter-API
Author-email: tschoerk <tschoerk@proton.me>
License-Expression: MIT
License-File: LICENSE.txt
Classifier: Development Status :: 4 - Beta
Classifier: Programming Language :: Python
Classifier: Programming Language :: Python :: 3.9
Classifier: Programming Language :: Python :: 3.10
Classifier: Programming Language :: Python :: 3.11
Classifier: Programming Language :: Python :: 3.12
Classifier: Programming Language :: Python :: Implementation :: CPython
Classifier: Programming Language :: Python :: Implementation :: PyPy
Requires-Python: >=3.9
Requires-Dist: python-dateutil>=2.8.2
Requires-Dist: requests>=2.32.3
